<timestamp time="956666.666667">
   <occluded>
      <object id="5"/>
      <object id="11"/>
   </occluded>
   <object id="0">
      <position global="center center" x="318" y="367"/>
      <shape BestResponse="I">
         <distribution F="0.0" I="0.870185629834" L="0.000184776679042" N="0.0508921201851" P="4.04837660228e-06" T="0.0" U="0.0" V="0.0" W="0.0787334249249" X="0.0" Y="0.0" Z="0.0"/>
         <orientation value="-0.679140276672"/>
         <skewness horizontal="right-skewed" vertical="symmetric"/>
         <nbEdges value="4"/>
      </shape>
      <colour BestResponse="Blue">
         <distribution Blue="0.999710540541" Brown="4.91348210487e-05" Gray="1.05458196541e-06" Green="4.79145799359e-22" Orange="2.17769180146e-11" Pink="1.72711979723e-05" Purple="0.000218902370667" Red="3.09646538829e-06" Yellow="2.04079322382e-23"/>
         <hsvValue H="105.360839844" S="198.868164062" V="166.536621094"/>
         <rgbValue B="166.194335938" G="101.170410156" R="39.1552734375"/>
      </colour>
   </object>
   <object id="1">
      <position global="right top" x="333" y="142"/>
      <shape BestResponse="Z">
         <distribution F="0.0133546440862" I="3.86971455545e-57" L="0.0380454643885" N="0.252067446343" P="1.24788583068e-10" T="1.79628998821e-09" U="6.17425808733e-07" V="0.0" W="2.36715943422e-05" X="0.00333543641959" Y="0.201026909104" Z="0.492145808718"/>
         <orientation value="44.0756991023"/>
         <skewness horizontal="symmetric" vertical="bottom-skewed"/>
         <nbEdges value="8"/>
      </shape>
      <colour BestResponse="Brown">
         <distribution Blue="7.4144242613e-23" Brown="0.818873594934" Gray="0.00205758429517" Green="2.12822926264e-15" Orange="0.11802212192" Pink="0.0424907021829" Purple="4.19001142616e-20" Red="0.0162233800586" Yellow="0.00233261660942"/>
         <hsvValue H="12.1883276116" S="91.1221186856" V="123.475232957"/>
         <rgbValue B="81.3084845513" G="96.0990681707" R="122.769004414"/>
      </colour>
   </object>
   <object id="2">
      <position global="right center" x="330" y="323"/>
      <shape BestResponse="X">
         <distribution F="4.30379802442e-05" I="0.0" L="0.0" N="0.0" P="0.205474787422" T="1.37119226483e-06" U="0.0" V="2.86206076307e-08" W="8.06017875007e-25" X="0.794480774784" Y="1.20902681251e-24" Z="0.0"/>
         <orientation value="-0.803592527756"/>
         <skewness horizontal="symmetric" vertical="symmetric"/>
         <nbEdges value="12"/>
      </shape>
      <colour BestResponse="Red">
         <distribution Blue="9.03177026271e-43" Brown="0.262331888145" Gray="8.14973448894e-07" Green="1.29826634134e-31" Orange="0.224296240933" Pink="0.0563798214933" Purple="8.73287921592e-29" Red="0.456986940325" Yellow="4.29413110937e-06"/>
         <hsvValue H="7.04621435595" S="167.861848574" V="167.082104228"/>
         <rgbValue B="59.9110127827" G="72.901179941" R="165.792035398"/>
      </colour>
   </object>
   <object id="3">
      <position global="center center" x="203" y="224"/>
      <shape BestResponse="N">
         <distribution F="2.29132988967e-20" I="7.192067156e-57" L="1.08097134314e-05" N="0.690815509691" P="1.05729152591e-19" T="0.0" U="0.0" V="0.0" W="0.294577213901" X="3.85670442693e-21" Y="0.0145964666943" Z="4.6230998555e-19"/>
         <orientation value="-0.526128593619"/>
         <skewness horizontal="right-skewed" vertical="symmetric"/>
         <nbEdges value="8"/>
      </shape>
      <colour BestResponse="Purple">
         <distribution Blue="0.0918805983145" Brown="1.04263217722e-13" Gray="0.000364153172592" Green="2.20512131441e-25" Orange="2.70796519736e-11" Pink="0.0193449641" Purple="0.887445716083" Red="0.000964568302856" Yellow="7.04211319966e-23"/>
         <hsvValue H="124.769705603" S="132.237416904" V="135.265906933"/>
         <rgbValue B="134.902659069" G="67.1362773029" R="77.5185185185"/>
      </colour>
   </object>
   <object id="4">
      <position global="center top" x="224" y="83"/>
      <shape BestResponse="P">
         <distribution F="4.41291240402e-06" I="0.0" L="2.3059474502e-35" N="6.72078641462e-35" P="0.99999558707" T="1.10520547552e-28" U="0.0" V="0.0" W="1.11405285538e-29" X="1.79330645024e-11" Y="6.11491844848e-35" Z="9.07050966785e-34"/>
         <orientation value="-4.92164577322"/>
         <skewness horizontal="right-skewed" vertical="symmetric"/>
         <nbEdges value="6"/>
      </shape>
      <colour BestResponse="Pink">
         <distribution Blue="6.39754753538e-34" Brown="6.68480006953e-22" Gray="0.110625198337" Green="2.98653267071e-24" Orange="6.56285396107e-12" Pink="0.875067616894" Purple="0.013985300855" Red="0.000321883908234" Yellow="1.00077138376e-20"/>
         <hsvValue H="157.410531221" S="83.25722274" V="175.693383038"/>
         <rgbValue B="161.859273066" G="118.979496738" R="174.654706431"/>
      </colour>
   </object>
   <object id="5">
      <position global="left top" x="121" y="96"/>
      <shape BestResponse="N">
         <distribution F="1.02415757327e-18" I="8.78657007393e-36" L="0.00156859713532" N="0.667704650118" P="8.22723476809e-20" T="1.41396311904e-28" U="0.0" V="4.25878464504e-42" W="0.227959135621" X="3.58389245845e-62" Y="0.00291306290439" Z="0.099854554221"/>
         <orientation value="10.4812859474"/>
         <skewness horizontal="symmetric" vertical="bottom-skewed"/>
         <nbEdges value="10"/>
      </shape>
      <colour BestResponse="Green">
         <distribution Blue="6.25070670787e-15" Brown="0.000264350533686" Gray="0.0630154591044" Green="0.883223625633" Orange="0.000649838208891" Pink="0.00123063898543" Purple="1.95529269239e-23" Red="1.35884697061e-06" Yellow="0.0516147286876"/>
         <hsvValue H="53.1183800623" S="82.243435692" V="156.91811304"/>
         <rgbValue B="108.368491322" G="156.421005785" R="118.342679128"/>
      </colour>
   </object>
   <object id="6">
      <position global="center top" x="268" y="135"/>
      <shape BestResponse="F">
         <distribution F="0.814406501838" I="2.32212614071e-06" L="9.28850456282e-06" N="4.03391739368e-33" P="0.18555565943" T="7.46228044452e-06" U="9.20112202892e-06" V="6.37071643541e-06" W="1.49476547522e-16" X="8.21348874352e-09" Y="3.18576915124e-06" Z="1.84780177945e-28"/>
         <orientation value="0.981496650484"/>
         <skewness horizontal="symmetric" vertical="bottom-skewed"/>
         <nbEdges value="10"/>
      </shape>
      <colour BestResponse="Gray">
         <distribution Blue="0.176998373252" Brown="1.96169916831e-10" Gray="0.774059627067" Green="5.90565742183e-07" Orange="2.9512839891e-08" Pink="0.0488527242685" Purple="6.47092871546e-05" Red="2.39458486617e-05" Yellow="1.71839930399e-12"/>
         <hsvValue H="101.805996473" S="78.0868606702" V="143.874338624"/>
         <rgbValue B="144.292328042" G="126.845238095" R="100.318342152"/>
      </colour>
   </object>
   <object id="7">
      <position global="left top" x="121" y="97"/>
      <shape BestResponse="T">
         <distribution F="3.07170454371e-09" I="0.0" L="3.53928690856e-06" N="0.322495497532" P="2.06929379278e-36" T="0.467589427629" U="2.6739753296e-38" V="1.61668691132e-09" W="0.106744360713" X="6.52986218353e-15" Y="1.5418094729e-05" Z="0.103151752056"/>
         <orientation value="10.3541946009"/>
         <skewness horizontal="symmetric" vertical="bottom-skewed"/>
         <nbEdges value="10"/>
      </shape>
      <colour BestResponse="Green">
         <distribution Blue="0.0167790043228" Brown="1.79846548169e-05" Gray="0.118511963146" Green="0.861724358478" Orange="6.03747167402e-05" Pink="0.00117301320263" Purple="8.18634001059e-16" Red="1.43643880806e-06" Yellow="0.00173186504003"/>
         <hsvValue H="55.5663559698" S="77.7288060364" V="155.643586329"/>
         <rgbValue B="110.457612073" G="155.201065246" R="116.107856192"/>
      </colour>
   </object>
   <object id="8">
      <position global="right center" x="425" y="258"/>
      <shape BestResponse="U">
         <distribution F="0.05365764" I="0.0" L="1.11077869502e-62" N="0.043046721" P="1.08252591594e-42" T="1.65167470241e-19" U="0.592473103793" V="0.138780036252" W="5.02195835536e-23" X="0.1" Y="0.0720400247802" Z="2.47417543822e-06"/>
         <orientation value="-15.2621768857"/>
         <skewness horizontal="right-skewed" vertical="symmetric"/>
         <nbEdges value="10"/>
      </shape>
      <colour BestResponse="Yellow">
         <distribution Blue="2.50117328199e-41" Brown="0.00629319039281" Gray="0.000340545458278" Green="0.000832675915776" Orange="0.0659638968239" Pink="0.00138052419378" Purple="7.19373731817e-39" Red="1.34438234974e-05" Yellow="0.925175723392"/>
         <hsvValue H="28.7012987013" S="138.253837072" V="161.708382527"/>
         <rgbValue B="75.4256198347" G="156.397284534" R="160.491145218"/>
      </colour>
   </object>
   <object id="9">
      <position global="center top" x="206" y="171"/>
      <shape BestResponse="Z">
         <distribution F="0.0150094635307" I="0.0" L="1.17990304713e-13" N="0.0106561678568" P="1.04495682054e-05" T="2.57482218389e-13" U="1.74199485551e-11" V="0.000675146192997" W="0.355839490489" X="8.58274061297e-13" Y="0.0382138116546" Z="0.579595470689"/>
         <orientation value="3.24428624715"/>
         <skewness horizontal="symmetric" vertical="symmetric"/>
         <nbEdges value="8"/>
      </shape>
      <colour BestResponse="Blue">
         <distribution Blue="0.999705348704" Brown="0.000282098743069" Gray="7.22514267452e-06" Green="2.47487270116e-12" Orange="1.94328539512e-10" Pink="5.18606021677e-06" Purple="9.88046954704e-10" Red="1.40165512507e-07" Yellow="2.28196639748e-19"/>
         <hsvValue H="98.4233097881" S="188.085267407" V="162.573158426"/>
         <rgbValue B="161.760343088" G="128.416750757" R="44.4162462159"/>
      </colour>
   </object>
   <object id="10">
      <position global="center top" x="287" y="205"/>
      <shape BestResponse="L">
         <distribution F="0.0348678484607" I="3.69276580935e-26" L="0.95651250937" N="5.81945441987e-06" P="2.38104427959e-09" T="2.69613490668e-10" U="3.48134708084e-62" V="9.71564417179e-10" W="3.02702543052e-06" X="5.76318733778e-10" Y="0.00861079149124" Z="0.0"/>
         <orientation value="16.6036649432"/>
         <skewness horizontal="right-skewed" vertical="symmetric"/>
         <nbEdges value="6"/>
      </shape>
      <colour BestResponse="Orange">
         <distribution Blue="8.3024390037e-48" Brown="0.0258001515257" Gray="1.79200055548e-06" Green="2.18334621636e-16" Orange="0.532767101044" Pink="0.00469506008462" Purple="4.02084224812e-38" Red="0.00235036107415" Yellow="0.434385534271"/>
         <hsvValue H="17.8173823073" S="194.82876358" V="185.501810657"/>
         <rgbValue B="46.5431971029" G="127.999482669" R="183.871184687"/>
      </colour>
   </object>
   <object id="11">
      <position global="right center" x="496" y="277"/>
      <shape BestResponse="V">
         <distribution F="0.436088033892" I="8.82054230006e-10" L="0.00393908405407" N="2.2585945454e-05" P="9.1040125329e-15" T="1.09926675691e-41" U="7.2101026724e-09" V="0.549436747863" W="0.00295086155985" X="1.49403222772e-41" Y="0.00756224413768" Z="4.34455677383e-07"/>
         <orientation value="-40.5004629732"/>
         <skewness horizontal="right-skewed" vertical="top-skewed"/>
         <nbEdges value="6"/>
      </shape>
      <colour BestResponse="Blue">
         <distribution Blue="0.999805915796" Brown="0.000184165673178" Gray="3.25789380853e-06" Green="3.26173658111e-15" Orange="9.63143240437e-11" Pink="6.2820400689e-06" Purple="3.55574031435e-08" Red="3.42943025955e-07" Yellow="9.47811617633e-21"/>
         <hsvValue H="99.6691505216" S="211.958768008" V="159.569796324"/>
         <rgbValue B="159.516641828" G="117.033780427" R="28.5469448584"/>
      </colour>
   </object>
</timestamp>
