<timestamp time="2282433.17972">
   <boundingBox height="458" width="615" x="85" y="19"/>
   <object id="0">
      <position global="center center" x="328" y="246"/>
      <shape BestResponse="W">
         <distribution F="0.0" I="0.443799237993" L="1.11936807334e-06" N="1.96713761877e-08" P="0.0" T="0.0" U="1.41813115102e-45" V="4.25439345306e-45" W="0.556199622967" X="0.0" Y="1.41813115102e-45" Z="0.0"/>
         <orientation value="-2.29397359578"/>
         <skewness horizontal="symmetric" vertical="bottom-skewed"/>
         <nbEdges value="4"/>
      </shape>
      <colour BestResponse="Blue">
         <distribution Blue="0.982166630704" Brown="1.22025265015e-08" Gray="0.0163733137915" Green="1.21662257179e-08" Orange="5.15632778286e-09" Pink="0.00145902871752" Purple="2.06700928508e-08" Red="9.76591702595e-07" Yellow="2.63762461408e-14"/>
         <hsvValue H="98.3504132231" S="109.623966942" V="165.604132231"/>
         <rgbValue B="163.607438017" G="145.578512397" R="95.6826446281"/>
      </colour>
   </object>
   <object id="1">
      <position global="left center" x="195" y="241"/>
      <shape BestResponse="V">
         <distribution F="4.74114895377e-86" I="0.0" L="4.52156179095e-05" N="3.4127372985e-23" P="1.94609028965e-40" T="0.0" U="0.00555376876729" V="0.601439233022" W="4.69092401135e-40" X="0.0" Y="0.392961782593" Z="2.68881049325e-124"/>
         <orientation value="41.0635546228"/>
         <skewness horizontal="right-skewed" vertical="top-skewed"/>
         <nbEdges value="6"/>
      </shape>
      <colour BestResponse="Blue">
         <distribution Blue="0.96108849659" Brown="0.00060310500474" Gray="0.000254829313574" Green="0.0380468421731" Orange="3.95105143853e-09" Pink="6.71691190427e-06" Purple="1.79629862537e-15" Red="6.05509945191e-09" Yellow="9.10668252961e-14"/>
         <hsvValue H="89.771577381" S="172.795386905" V="172.672619048"/>
         <rgbValue B="166.921130952" G="169.011160714" R="58.8831845238"/>
      </colour>
   </object>
   <object id="2">
      <position global="center center" x="236" y="274"/>
      <shape BestResponse="L">
         <distribution F="8.41443856284e-09" I="3.9672578606e-09" L="0.549590421049" N="0.203031839276" P="4.04003242176e-13" T="5.81997956179e-09" U="0.00177259668461" V="1.61666098939e-09" W="1.9314172171e-05" X="5.94693397091e-29" Y="0.245585808999" Z="6.80131887436e-15"/>
         <orientation value="1.38971705755"/>
         <skewness horizontal="left-skewed" vertical="bottom-skewed"/>
         <nbEdges value="8"/>
      </shape>
      <colour BestResponse="Orange">
         <distribution Blue="6.2277766793e-59" Brown="0.0311128708533" Gray="2.27023171123e-07" Green="2.89432035829e-20" Orange="0.859414866277" Pink="0.00683915092364" Purple="2.27476338194e-43" Red="0.0191516341896" Yellow="0.0834812507329"/>
         <hsvValue H="14.7442207308" S="198.418344519" V="182.460850112"/>
         <rgbValue B="41.1543624161" G="110.083519761" R="180.6748695"/>
      </colour>
   </object>
   <object id="3">
      <position global="center bottom" x="248" y="314"/>
      <shape BestResponse="Z">
         <distribution F="7.64174093928e-08" I="2.94400309117e-18" L="9.25769384421e-12" N="0.162382398663" P="0.0" T="1.1429228156e-11" U="2.35250343652e-09" V="5.46656439642e-12" W="0.0658873809946" X="3.26779619885e-171" Y="0.00218892804254" Z="0.769541213504"/>
         <orientation value="28.6822580817"/>
         <skewness horizontal="left-skewed" vertical="symmetric"/>
         <nbEdges value="8"/>
      </shape>
      <colour BestResponse="Blue">
         <distribution Blue="0.499796831194" Brown="6.20154758017e-05" Gray="0.000930164841316" Green="0.499200128635" Orange="6.05752863544e-08" Pink="1.07907922824e-05" Purple="4.62137306298e-19" Red="8.10851876403e-09" Yellow="3.77673279315e-10"/>
         <hsvValue H="80.9517326733" S="146.506188119" V="162.34220297"/>
         <rgbValue B="134.551980198" G="160.858910891" R="72.4059405941"/>
      </colour>
   </object>
   <object id="4">
      <position global="center bottom" x="305" y="329"/>
      <shape BestResponse="W">
         <distribution F="3.7512432703e-64" I="2.6182091372e-163" L="0.0131220000167" N="0.375391033012" P="3.69225895234e-12" T="0.0" U="2.25397256007e-56" V="0.0" W="0.479945673516" X="0.0" Y="0.047620989937" Z="0.0839203035137"/>
         <orientation value="42.5693781249"/>
         <skewness horizontal="right-skewed" vertical="bottom-skewed"/>
         <nbEdges value="9"/>
      </shape>
      <colour BestResponse="Green">
         <distribution Blue="3.67090870883e-40" Brown="0.00174162624825" Gray="7.83900119103e-05" Green="0.48476812886" Orange="0.0286711791688" Pink="3.9703486896e-06" Purple="6.07478272232e-49" Red="2.74519099e-09" Yellow="0.484736702617"/>
         <hsvValue H="39.9828134946" S="194.323997454" V="205.222151496"/>
         <rgbValue B="50.9147040102" G="204.581795035" R="154.313812858"/>
      </colour>
   </object>
   <object id="5">
      <position global="right top" x="449" y="135"/>
      <shape BestResponse="N">
         <distribution F="1.06083904328e-12" I="1.07591177662e-13" L="0.389912186798" N="0.538031957492" P="2.81734440555e-14" T="0.0" U="4.06683076041e-12" V="1.28822893814e-13" W="0.0438129019076" X="0.0" Y="0.0282429537967" Z="3.53944669194e-13"/>
         <orientation value="7.62736341966"/>
         <skewness horizontal="left-skewed" vertical="top-skewed"/>
         <nbEdges value="9"/>
      </shape>
      <colour BestResponse="Yellow">
         <distribution Blue="2.88282592675e-79" Brown="0.000167133409906" Gray="1.73910481284e-07" Green="0.0168450370276" Orange="0.45921321038" Pink="8.83081249825e-05" Purple="1.88030534578e-63" Red="1.53642684802e-06" Yellow="0.52368460072"/>
         <hsvValue H="23.6575342466" S="234.427039905" V="223.203097082"/>
         <rgbValue B="21.7689100655" G="181.029184038" R="222.34842168"/>
      </colour>
   </object>
   <object id="6">
      <position global="center top" x="370" y="136"/>
      <shape BestResponse="P">
         <distribution F="0.0958017998001" I="0.0" L="0.0" N="0.0" P="0.904146841954" T="9.44824675588e-45" U="2.0430156962e-83" V="0.0" W="3.88266708023e-05" X="1.25315749651e-05" Y="0.0" Z="0.0"/>
         <orientation value="-19.9010485699"/>
         <skewness horizontal="symmetric" vertical="bottom-skewed"/>
         <nbEdges value="4"/>
      </shape>
      <colour BestResponse="Brown">
         <distribution Blue="3.61599264879e-41" Brown="0.506198145312" Gray="0.00145317439752" Green="4.2407488174e-21" Orange="0.251801594491" Pink="0.185100101193" Purple="2.4445383674e-32" Red="0.00206379300258" Yellow="0.0533831916033"/>
         <hsvValue H="10.6167494677" S="90.9162526615" V="222.18807665"/>
         <rgbValue B="144.101490419" G="171.656493967" R="222.532292406"/>
      </colour>
   </object>
   <object id="7">
      <position global="center center" x="396" y="270"/>
      <shape BestResponse="N">
         <distribution F="1.74444620757e-111" I="2.8061666962e-20" L="0.219174552797" N="0.34907802541" P="2.61666912698e-111" T="0.0" U="0.0" V="0.0" W="0.318208879552" X="0.0" Y="0.113538542241" Z="4.74025592987e-21"/>
         <orientation value="22.8681302462"/>
         <skewness horizontal="right-skewed" vertical="bottom-skewed"/>
         <nbEdges value="8"/>
      </shape>
      <colour BestResponse="Gray">
         <distribution Blue="2.84165205748e-27" Brown="8.53553730442e-22" Gray="0.489487587992" Green="6.3354781518e-09" Orange="7.44170003512e-11" Pink="0.302629381111" Purple="0.207787594322" Red="9.54301648598e-05" Yellow="3.95235178202e-16"/>
         <hsvValue H="152.109969789" S="66.7208459215" V="125.836253776"/>
         <rgbValue B="104.284592145" G="94.6060422961" R="126.572809668"/>
      </colour>
   </object>
   <object id="8">
      <position global="left center" x="59" y="214"/>
      <shape BestResponse="W">
         <distribution F="0.0257472577335" I="0.0131416026488" L="0.00591639265662" N="0.108674301424" P="0.0730115094096" T="0.000501764695003" U="5.25649869195e-13" V="1.21589019572e-59" W="0.710129484293" X="5.51095009577e-06" Y="0.0628036157556" Z="6.85604335465e-05"/>
         <orientation value="40.825629042"/>
         <skewness horizontal="symmetric" vertical="symmetric"/>
         <nbEdges value="9"/>
      </shape>
      <colour BestResponse="Yellow">
         <distribution Blue="1.95616566791e-49" Brown="0.00387489978792" Gray="1.63385564824e-06" Green="2.28114141511e-14" Orange="0.365866787924" Pink="0.00436737493171" Purple="1.84184767544e-40" Red="0.000516484259427" Yellow="0.625372819241"/>
         <hsvValue H="17.8083801737" S="175.009197752" V="221.040878896"/>
         <rgbValue B="70.4869698518" G="158.804292284" R="219.782830864"/>
      </colour>
   </object>
   <object id="9">
      <position global="center center" x="295" y="247"/>
      <shape BestResponse="T">
         <distribution F="0.00741275082026" I="0.0" L="1.14781495507e-95" N="8.25080236528e-27" P="3.35643993541e-81" T="0.924015855383" U="5.79374189193e-25" V="0.0685713937969" W="1.16932808571e-32" X="5.77445968251e-33" Y="1.36583335081e-24" Z="1.63046024733e-136"/>
         <orientation value="0.338818231056"/>
         <skewness horizontal="left-skewed" vertical="symmetric"/>
         <nbEdges value="8"/>
      </shape>
      <colour BestResponse="Green">
         <distribution Blue="2.4440053614e-25" Brown="0.00107296128887" Gray="0.0011936482929" Green="0.501467563764" Orange="0.00174066889076" Pink="2.34403803207e-05" Purple="1.40588405134e-37" Red="1.36638841241e-08" Yellow="0.49450170372"/>
         <hsvValue H="46.4501992032" S="147.450199203" V="188.376095618"/>
         <rgbValue B="80.209561753" G="186.231075697" R="128.951394422"/>
      </colour>
   </object>
   <object id="10">
      <position global="center center" x="210" y="209"/>
      <shape BestResponse="U">
         <distribution F="4.03266563757e-20" I="5.47727744171e-16" L="1.54585673392e-07" N="4.77860098623e-63" P="4.04505165663e-60" T="0.0" U="0.649926227157" V="0.124446541823" W="1.82406891209e-08" X="3.30418822407e-86" Y="0.137223997941" Z="0.0884030602523"/>
         <orientation value="-4.51240031537"/>
         <skewness horizontal="right-skewed" vertical="bottom-skewed"/>
         <nbEdges value="9"/>
      </shape>
      <colour BestResponse="Yellow">
         <distribution Blue="4.78861446627e-63" Brown="0.000206535618449" Gray="1.91116360007e-05" Green="0.387504271449" Orange="0.22472514524" Pink="4.06107360758e-05" Purple="3.99154792842e-58" Red="1.19958506775e-08" Yellow="0.387504313324"/>
         <hsvValue H="30.1370689655" S="190.28362069" V="223.713793103"/>
         <rgbValue B="59.6413793103" G="222.051724138" R="220.751724138"/>
      </colour>
   </object>
   <object id="11">
      <position global="center center" x="245" y="223"/>
      <shape BestResponse="V">
         <distribution F="0.45029908322" I="0.000985392196096" L="0.00109488021788" N="1.02609894013e-22" P="2.74276246698e-22" T="0.00384050762434" U="0.0637950692779" V="0.462058771259" W="0.00065692813073" X="0.000811022383618" Y="0.0138048981445" Z="0.00265344754561"/>
         <orientation value="-34.6866265042"/>
         <skewness horizontal="symmetric" vertical="bottom-skewed"/>
         <nbEdges value="11"/>
      </shape>
      <colour BestResponse="Yellow">
         <distribution Blue="8.36221307863e-22" Brown="0.00308053366431" Gray="0.374291186063" Green="0.0313191093321" Orange="0.0115997174271" Pink="0.0345504177912" Purple="2.85972491805e-23" Red="2.97941421352e-05" Yellow="0.54512924158"/>
         <hsvValue H="37.9763113367" S="70.9915397631" V="169.633671743"/>
         <rgbValue B="122.283417936" G="169.423857868" R="156.925549915"/>
      </colour>
   </object>
</timestamp>
