<timestamp time="2648737.32719">
   <boundingBox height="458" width="615" x="85" y="19"/>
   <occluded>
      <object id="0"/>
      <object id="10"/>
   </occluded>
   <object id="0">
      <position global="left center" x="68" y="245"/>
      <shape BestResponse="I">
         <distribution F="0.0" I="0.66475976967" L="8.39591226762e-12" N="9.55619371645e-12" P="0.0" T="0.0" U="3.2175648285e-74" V="9.65269448549e-74" W="0.335240230312" X="0.0" Y="3.2175648285e-74" Z="0.0"/>
         <orientation value="30.2599438656"/>
         <skewness horizontal="left-skewed" vertical="bottom-skewed"/>
         <nbEdges value="4"/>
      </shape>
      <colour BestResponse="Blue">
         <distribution Blue="0.978324756125" Brown="8.05282602479e-09" Gray="0.0199096198402" Green="2.22436661155e-08" Orange="6.88710900011e-09" Pink="0.00176424756763" Purple="1.34956475376e-08" Red="1.32578736053e-06" Yellow="4.88054301442e-14"/>
         <hsvValue H="97.5581210191" S="102.302547771" V="153.737261146"/>
         <rgbValue B="152.300159236" G="137.871019108" R="94.8853503185"/>
      </colour>
   </object>
   <object id="1">
      <position global="left top" x="61" y="131"/>
      <shape BestResponse="V">
         <distribution F="2.35014827763e-118" I="0.0" L="2.05384407164e-14" N="1.69166561993e-55" P="9.64660842113e-73" T="0.0" U="0.000867391160931" V="0.764569202396" W="6.27369617165e-07" X="0.0" Y="0.234562779074" Z="1.33282109699e-156"/>
         <orientation value="-37.6460135442"/>
         <skewness horizontal="right-skewed" vertical="top-skewed"/>
         <nbEdges value="7"/>
      </shape>
      <colour BestResponse="Blue">
         <distribution Blue="0.939956705205" Brown="0.000405039740721" Gray="0.000635969547206" Green="0.058993060106" Orange="3.95911049522e-09" Pink="9.2187489404e-06" Purple="5.17898226194e-16" Red="2.69309174942e-09" Yellow="1.94568331836e-13"/>
         <hsvValue H="89.2110799439" S="151.455820477" V="181.825385694"/>
         <rgbValue B="177.010518934" G="180.120617111" R="76.7805049088"/>
      </colour>
   </object>
   <object id="2">
      <position global="center center" x="331" y="284"/>
      <shape BestResponse="Y">
         <distribution F="5.86073541672e-05" I="0.0705725162762" L="0.245693066486" N="0.0408630343663" P="0.00013360495102" T="0.0254311898586" U="0.00743906368851" V="0.00258491589578" W="0.0412609406164" X="2.14539421034e-09" Y="0.545825539439" Z="0.0201375189228"/>
         <orientation value="3.0069684336"/>
         <skewness horizontal="right-skewed" vertical="top-skewed"/>
         <nbEdges value="8"/>
      </shape>
      <colour BestResponse="Orange">
         <distribution Blue="2.06741574044e-43" Brown="0.0513821094507" Gray="7.71966181908e-07" Green="8.844024427e-18" Orange="0.828874912986" Pink="0.0076099066466" Purple="2.33559314927e-36" Red="0.0152821990992" Yellow="0.0968500998509"/>
         <hsvValue H="15.0483443709" S="203.065562914" V="184.291390728"/>
         <rgbValue B="41.1894039735" G="113.213907285" R="183.632450331"/>
      </colour>
   </object>
   <object id="3">
      <position global="right top" x="446" y="127"/>
      <shape BestResponse="Z">
         <distribution F="1.49665217119e-18" I="5.8419542456e-42" L="5.23137854918e-08" N="0.0381907508357" P="0.0" T="2.26796731804e-35" U="2.83213540641e-07" V="7.61887417213e-18" W="0.0680857641041" X="6.48447548675e-195" Y="7.03201035629e-06" Z="0.893716117523"/>
         <orientation value="-42.7089838334"/>
         <skewness horizontal="symmetric" vertical="symmetric"/>
         <nbEdges value="9"/>
      </shape>
      <colour BestResponse="Blue">
         <distribution Blue="0.497854956522" Brown="3.54591133395e-05" Gray="0.00435363699136" Green="0.49773457705" Orange="7.77797690731e-08" Pink="2.12859274396e-05" Purple="1.1014926999e-19" Red="3.69748604967e-09" Yellow="2.91874763691e-09"/>
         <hsvValue H="80.0469314079" S="126.416606498" V="177.563176895"/>
         <rgbValue B="148.82599278" G="177.196389892" R="91.0635379061"/>
      </colour>
   </object>
   <object id="4">
      <position global="center top" x="234" y="110"/>
      <shape BestResponse="W">
         <distribution F="2.4838301362e-84" I="1.73360837708e-183" L="0.0480931670322" N="0.284191532293" P="2.44477454424e-32" T="0.0" U="1.49243452569e-76" V="0.0" W="0.665302041267" X="0.0" Y="0.00241314804846" Z="1.11359447392e-07"/>
         <orientation value="-28.772638962"/>
         <skewness horizontal="left-skewed" vertical="top-skewed"/>
         <nbEdges value="10"/>
      </shape>
      <colour BestResponse="Green">
         <distribution Blue="5.86722322915e-44" Brown="0.000792046380707" Gray="0.000456890301586" Green="0.482485477981" Orange="0.0337263651689" Pink="5.66915844104e-05" Purple="6.79120445358e-50" Red="6.03641346709e-09" Yellow="0.482482522547"/>
         <hsvValue H="36.2140495868" S="151.099173554" V="222.738842975"/>
         <rgbValue B="93.2190082645" G="222.265289256" R="194.882644628"/>
      </colour>
   </object>
   <object id="5">
      <position global="center top" x="380" y="104"/>
      <shape BestResponse="L">
         <distribution F="9.38321310592e-06" I="0.296870507119" L="0.70214290634" N="2.33307434492e-10" P="5.93229778891e-41" T="0.0" U="0.000977178487407" V="9.96273778243e-09" W="1.22986341476e-12" X="0.0" Y="1.46424046004e-08" Z="7.45278132954e-40"/>
         <orientation value="12.0999441655"/>
         <skewness horizontal="right-skewed" vertical="top-skewed"/>
         <nbEdges value="6"/>
      </shape>
      <colour BestResponse="Yellow">
         <distribution Blue="1.12133210823e-72" Brown="0.000128406274398" Gray="1.75726997139e-06" Green="0.359804778312" Orange="0.280178269487" Pink="3.85405176519e-05" Purple="1.58603883229e-62" Red="6.35536829069e-08" Yellow="0.359848184585"/>
         <hsvValue H="27.5058333333" S="210.68" V="223.433333333"/>
         <rgbValue B="41.2708333333" G="207.333333333" R="222.874166667"/>
      </colour>
   </object>
   <object id="6">
      <position global="right center" x="486" y="172"/>
      <shape BestResponse="P">
         <distribution F="5.50748750463e-05" I="0.0" L="0.0" N="0.0" P="0.981923166117" T="8.18810838265e-20" U="1.31186390021e-105" V="0.0" W="1.27273452933e-18" X="0.018021759008" Y="0.0" Z="0.0"/>
         <orientation value="26.9230119932"/>
         <skewness horizontal="right-skewed" vertical="symmetric"/>
         <nbEdges value="6"/>
      </shape>
      <colour BestResponse="Brown">
         <distribution Blue="3.08393486935e-47" Brown="0.429312508226" Gray="5.05688153262e-05" Green="1.68159368697e-29" Orange="0.280100313272" Pink="0.238674618793" Purple="8.33441576417e-32" Red="0.0513005110238" Yellow="0.000561479869862"/>
         <hsvValue H="3.91546391753" S="112.857731959" V="223.379381443"/>
         <rgbValue B="124.947766323" G="138.192439863" R="222.817182131"/>
      </colour>
   </object>
   <object id="7">
      <position global="left center" x="177" y="257"/>
      <shape BestResponse="N">
         <distribution F="9.7765941007e-136" I="0.00148920085925" L="0.247741375496" N="0.44711560257" P="0.00011452833794" T="0.0" U="1.10748813889e-21" V="0.0" W="0.226964775279" X="0.0" Y="0.0765744947626" Z="2.2695167816e-08"/>
         <orientation value="19.9785107792"/>
         <skewness horizontal="right-skewed" vertical="top-skewed"/>
         <nbEdges value="8"/>
      </shape>
      <colour BestResponse="Pink">
         <distribution Blue="2.60674129039e-28" Brown="1.27906981336e-22" Gray="0.361263681249" Green="4.02941608842e-11" Orange="1.74908124147e-11" Pink="0.361813583887" Purple="0.276759006114" Red="0.000163728692395" Yellow="2.44635648523e-18"/>
         <hsvValue H="158.434103261" S="76.0889945652" V="131.659646739"/>
         <rgbValue B="116.575407609" G="94.6012228261" R="132.292798913"/>
      </colour>
   </object>
   <object id="8">
      <position global="left center" x="129" y="243"/>
      <shape BestResponse="X">
         <distribution F="0.0421185955768" I="1.14174436192e-14" L="1.8220898209e-10" N="1.43226257542e-14" P="0.00341078750278" T="7.47420195326e-21" U="2.08047302064e-24" V="5.28161681064e-23" W="2.9095575242e-14" X="0.954470616725" Y="6.97441367183e-13" Z="1.28511830708e-11"/>
         <orientation value="27.516047013"/>
         <skewness horizontal="left-skewed" vertical="top-skewed"/>
         <nbEdges value="11"/>
      </shape>
      <colour BestResponse="Orange">
         <distribution Blue="4.14749484078e-66" Brown="0.00166119165555" Gray="4.14746979696e-08" Green="1.60435129606e-23" Orange="0.736547928617" Pink="0.0111162465715" Purple="3.59634604914e-49" Red="0.0249828592132" Yellow="0.225691732468"/>
         <hsvValue H="13.2580919932" S="214.63713799" V="224.019591141"/>
         <rgbValue B="38.7904599659" G="120.415672913" R="223.04088586"/>
      </colour>
   </object>
   <object id="9">
      <position global="center center" x="375" y="156"/>
      <shape BestResponse="T">
         <distribution F="7.3997697007e-06" I="0.0" L="5.68962368828e-128" N="4.08985441227e-59" P="1.66375948321e-113" T="0.85532690353" U="1.65676295825e-28" V="0.1446656967" W="5.79626249545e-65" X="2.86235184961e-65" Y="6.77032282309e-57" Z="8.08205643687e-169"/>
         <orientation value="43.451778009"/>
         <skewness horizontal="left-skewed" vertical="bottom-skewed"/>
         <nbEdges value="8"/>
      </shape>
      <colour BestResponse="Green">
         <distribution Blue="6.05282828262e-25" Brown="0.000966880934304" Gray="0.00180230077496" Green="0.502093004246" Orange="0.00140046532145" Pink="2.98141804323e-05" Purple="4.68311840237e-38" Red="1.19237043961e-08" Yellow="0.49370752262"/>
         <hsvValue H="45.7776993649" S="144.464361327" V="181.741707833"/>
         <rgbValue B="81.2180663373" G="181.432604093" R="129.249117855"/>
      </colour>
   </object>
   <object id="10">
      <position global="left center" x="187" y="194"/>
      <shape BestResponse="U">
         <distribution F="5.10209584866e-39" I="6.92980698349e-35" L="0.0356736252492" N="0.018" P="5.11776653949e-79" T="0.0" U="0.53800721816" V="0.0745268955226" W="2.30779718937e-27" X="4.18043213505e-105" Y="0.284279951562" Z="0.0495123095066"/>
         <orientation value="31.4420215206"/>
         <skewness horizontal="left-skewed" vertical="bottom-skewed"/>
         <nbEdges value="10"/>
      </shape>
      <colour BestResponse="Yellow">
         <distribution Blue="4.21015524617e-35" Brown="0.000326759475521" Gray="0.00010017854273" Green="0.39107513927" Orange="0.208061941138" Pink="0.00015091214831" Purple="1.37595635336e-32" Red="6.56585497858e-07" Yellow="0.400284412839"/>
         <hsvValue H="30.1391941392" S="187.523809524" V="223.941391941"/>
         <rgbValue B="63.1336996337" G="222.904761905" R="222.313186813"/>
      </colour>
   </object>
   <object id="11">
      <position global="center center" x="401" y="210"/>
      <shape BestResponse="F">
         <distribution F="0.597843793943" I="9.09987625248e-09" L="2.05466766246e-09" N="1.00308106181e-08" P="3.35568637051e-07" T="0.181742617953" U="0.00120258060223" V="0.219123137774" W="1.32462701485e-08" X="1.8522774262e-07" Y="8.72958247494e-05" Z="1.86752803161e-08"/>
         <orientation value="-34.3067236656"/>
         <skewness horizontal="left-skewed" vertical="bottom-skewed"/>
         <nbEdges value="10"/>
      </shape>
      <colour BestResponse="Gray">
         <distribution Blue="1.57538048113e-21" Brown="0.00376841695836" Gray="0.486861163456" Green="0.0248336556629" Orange="0.0136881628694" Pink="0.0470213308156" Purple="8.04758566032e-22" Red="4.74213152121e-05" Yellow="0.423779848923"/>
         <hsvValue H="38.985426787" S="70.9215822346" V="163.505898681"/>
         <rgbValue B="118.826509368" G="163.477446218" R="150.294240111"/>
      </colour>
   </object>
</timestamp>
