<timestamp time="1194185.02203">
   <boundingBox height="455" width="585" x="47" y="16"/>
   <occluded>
      <object id="6"/>
      <object id="9"/>
      <object id="0"/>
      <object id="2"/>
   </occluded>
   <object id="0">
      <position global="center center" x="264" y="241"/>
      <shape BestResponse="Z">
         <distribution F="0.0200006397714" I="3.20835943069e-89" L="1.87779806665e-08" N="0.0177475251073" P="2.34738524917e-23" T="0.0" U="2.82449686628e-05" V="0.0200824035757" W="0.263549548857" X="0.0" Y="0.263418385609" Z="0.415173233332"/>
         <orientation value="36.0005589931"/>
         <skewness horizontal="left-skewed" vertical="top-skewed"/>
         <nbEdges value="6"/>
      </shape>
      <colour BestResponse="Blue">
         <distribution Blue="0.999614969575" Brown="0.000382435042338" Gray="2.74858851438e-07" Green="4.37523542961e-14" Orange="1.89942387998e-10" Pink="1.56035866192e-06" Purple="4.05956313131e-10" Red="7.59569583807e-07" Yellow="6.66714236361e-21"/>
         <hsvValue H="98.3268206039" S="247.148312611" V="123.998223801"/>
         <rgbValue B="123.957371226" G="90.9671403197" R="6.90763765542"/>
      </colour>
   </object>
   <object id="1">
      <position global="center center" x="241" y="268"/>
      <shape BestResponse="L">
         <distribution F="0.000519187855489" I="0.240452903209" L="0.581984163686" N="0.151073390333" P="2.56746809035e-28" T="1.0498051951e-44" U="1.64439326682e-05" V="1.24335615996e-28" W="0.0227285547988" X="6.41863915443e-29" Y="0.00302247267006" Z="0.000202883514811"/>
         <orientation value="44.1209613959"/>
         <skewness horizontal="symmetric" vertical="bottom-skewed"/>
         <nbEdges value="6"/>
      </shape>
      <colour BestResponse="Orange">
         <distribution Blue="1.12906950504e-69" Brown="0.25039810582" Gray="2.31037373558e-07" Green="2.29434503326e-17" Orange="0.711582686158" Pink="0.00254378596737" Purple="2.77348697955e-39" Red="0.0218051765449" Yellow="0.0136700144723"/>
         <hsvValue H="16.9319114028" S="221.264150943" V="147.26168991"/>
         <rgbValue B="24.0328137818" G="92.3158326497" R="145.74733388"/>
      </colour>
   </object>
   <object id="2">
      <position global="center bottom" x="281" y="359"/>
      <shape BestResponse="V">
         <distribution F="0.0839911408709" I="0.249266036638" L="0.130012188237" N="0.0200070785738" P="0.0450056781178" T="4.38247258948e-47" U="0.00270170343535" V="0.249742674985" W="0.0551219156231" X="0.036" Y="0.125449880083" Z="0.00270170343535"/>
         <orientation value="19.9442775657"/>
         <skewness horizontal="right-skewed" vertical="top-skewed"/>
         <nbEdges value="11"/>
      </shape>
      <colour BestResponse="Blue">
         <distribution Blue="0.999931637738" Brown="4.71651108777e-05" Gray="3.83042071993e-08" Green="1.0902524178e-17" Orange="9.58890876929e-11" Pink="3.10793694175e-06" Purple="3.15890200033e-06" Red="1.4891912449e-05" Yellow="9.18384788924e-23"/>
         <hsvValue H="100.649322493" S="251.013550136" V="119.12899729"/>
         <rgbValue B="118.318699187" G="78.3837398374" R="4.42113821138"/>
      </colour>
   </object>
   <object id="3">
      <position global="left top" x="89" y="145"/>
      <shape BestResponse="T">
         <distribution F="3.08989017567e-07" I="0.0" L="1.49397502029e-72" N="1.01192836995e-80" P="1.05088875641e-40" T="0.999997519364" U="1.00265666923e-30" V="2.17164671154e-06" W="6.42186609759e-81" X="9.4579988077e-41" Y="1.2244209674e-29" Z="4.08397818998e-31"/>
         <orientation value="24.4540088533"/>
         <skewness horizontal="left-skewed" vertical="top-skewed"/>
         <nbEdges value="8"/>
      </shape>
      <colour BestResponse="Blue">
         <distribution Blue="0.524306704391" Brown="5.53792519992e-07" Gray="0.0116646383416" Green="0.463696811678" Orange="1.15906070637e-06" Pink="0.000325684981361" Purple="2.29222944222e-13" Red="4.4175714019e-06" Yellow="3.01828174285e-08"/>
         <hsvValue H="77.24" S="121.957538462" V="102.812307692"/>
         <rgbValue B="83.4529230769" G="102.432615385" R="54.296"/>
      </colour>
   </object>
   <object id="4">
      <position global="left center" x="55" y="252"/>
      <shape BestResponse="W">
         <distribution F="4.49459084318e-15" I="2.95301256294e-23" L="2.02214707284e-19" N="0.422615043386" P="1.23202398572e-08" T="0.0" U="4.55286509667e-25" V="0.0" W="0.531415796217" X="0.0" Y="0.000328490291602" Z="0.0456406577852"/>
         <orientation value="-3.8825992153"/>
         <skewness horizontal="symmetric" vertical="top-skewed"/>
         <nbEdges value="10"/>
      </shape>
      <colour BestResponse="Green">
         <distribution Blue="2.85773335396e-12" Brown="0.0002814923233" Gray="0.0123803925617" Green="0.984528324615" Orange="0.000427282690694" Pink="0.000579335269919" Purple="1.68012158588e-21" Red="1.03192939444e-05" Yellow="0.00179285324212"/>
         <hsvValue H="51.8048780488" S="112.137266024" V="115.907543959"/>
         <rgbValue B="67.6971072036" G="115.712422008" R="80.355076574"/>
      </colour>
   </object>
   <object id="5">
      <position global="right center" x="437" y="274"/>
      <shape BestResponse="P">
         <distribution F="0.000116428958922" I="0.0" L="0.0" N="2.48158691324e-36" P="0.978835962148" T="9.1166887712e-13" U="2.15777294602e-05" V="3.53635004126e-05" W="0.0208109664699" X="0.000179701029991" Y="3.74935829658e-11" Z="1.24788534609e-10"/>
         <orientation value="-17.6648198795"/>
         <skewness horizontal="right-skewed" vertical="symmetric"/>
         <nbEdges value="6"/>
      </shape>
      <colour BestResponse="Purple">
         <distribution Blue="1.98848818816e-37" Brown="2.16977769242e-21" Gray="0.0164042980535" Green="1.93909723377e-22" Orange="7.80121204792e-12" Pink="0.463926670821" Purple="0.517861680771" Red="0.00180735034661" Yellow="2.1714423429e-21"/>
         <hsvValue H="158.071626874" S="111.866185453" V="127.569128262"/>
         <rgbValue B="113.017767907" G="72.9772348695" R="126.725152693"/>
      </colour>
   </object>
   <object id="6">
      <position global="left bottom" x="186" y="342"/>
      <shape BestResponse="V">
         <distribution F="0.0193315438111" I="7.15970385178e-45" L="0.0357255586348" N="0.189350760206" P="0.118697814" T="6.49303056392e-31" U="0.0316627047565" V="0.317003073754" W="0.0279069922872" X="0.0" Y="0.117690021513" Z="0.142631531037"/>
         <orientation value="22.0167446478"/>
         <skewness horizontal="symmetric" vertical="symmetric"/>
         <nbEdges value="8"/>
      </shape>
      <colour BestResponse="Blue">
         <distribution Blue="0.999533582976" Brown="0.000449994072995" Gray="1.13298276027e-07" Green="1.91111735656e-16" Orange="1.79792848412e-10" Pink="4.34395180118e-06" Purple="1.16333883755e-08" Red="1.19538872916e-05" Yellow="1.17419968037e-21"/>
         <hsvValue H="100.165103189" S="244.869293308" V="112.681050657"/>
         <rgbValue B="112.761100688" G="77.3120700438" R="6.61475922452"/>
      </colour>
   </object>
   <object id="7">
      <position global="left top" x="149" y="135"/>
      <shape BestResponse="Y">
         <distribution F="3.59547293133e-08" I="7.38748045498e-08" L="0.34797881794" N="1.47107096445e-07" P="4.70338607244e-11" T="1.93554982405e-11" U="2.22367052017e-08" V="0.0732958073249" W="6.78377932757e-07" X="3.85319841175e-10" Y="0.578723676596" Z="7.40136520242e-07"/>
         <orientation value="-21.8158541284"/>
         <skewness horizontal="left-skewed" vertical="top-skewed"/>
         <nbEdges value="8"/>
      </shape>
      <colour BestResponse="Brown">
         <distribution Blue="1.04303859129e-31" Brown="0.874620009082" Gray="0.000439678200099" Green="3.17292032568e-14" Orange="0.0753150422391" Pink="0.0120844273359" Purple="1.48374221168e-19" Red="0.0372681200891" Yellow="0.000272723053744"/>
         <hsvValue H="10.5874337623" S="106.992429977" V="89.0113550341"/>
         <rgbValue B="53.0416351249" G="65.3444360333" R="88.0582891749"/>
      </colour>
   </object>
   <object id="8">
      <position global="center top" x="216" y="122"/>
      <shape BestResponse="X">
         <distribution F="0.104368696592" I="0.0" L="0.0" N="0.0" P="2.14954776685e-07" T="3.03502451655e-10" U="7.64179536613e-10" V="7.38747909398e-08" W="0.0" X="0.895631013511" Y="0.0" Z="0.0"/>
         <orientation value="38.4463259005"/>
         <skewness horizontal="symmetric" vertical="symmetric"/>
         <nbEdges value="11"/>
      </shape>
      <colour BestResponse="Red">
         <distribution Blue="1.52682318711e-63" Brown="0.0739323822132" Gray="4.21041309146e-06" Green="9.9957848046e-28" Orange="0.0710635604956" Pink="0.0935456778191" Purple="1.25743741451e-23" Red="0.76145393545" Yellow="2.33608670554e-07"/>
         <hsvValue H="9.03285151117" S="159.136005256" V="145.309461235"/>
         <rgbValue B="57.0650459921" G="61.4592641261" R="143.563074901"/>
      </colour>
   </object>
   <object id="9">
      <position global="left center" x="141" y="279"/>
      <shape BestResponse="N">
         <distribution F="0.0123534679286" I="0.000549790214234" L="0.159695202597" N="0.498330144086" P="0.00823564528379" T="5.702835586e-18" U="1.68216867888e-78" V="1.03340321474e-49" W="0.312493920946" X="0.0" Y="0.00785723199529" Z="0.000484596948705"/>
         <orientation value="3.60817991385"/>
         <skewness horizontal="symmetric" vertical="symmetric"/>
         <nbEdges value="8"/>
      </shape>
      <colour BestResponse="Purple">
         <distribution Blue="1.1604973962e-09" Brown="2.64454342086e-13" Gray="2.26883412311e-05" Green="2.21610747767e-24" Orange="3.27663412449e-11" Pink="0.00486116138551" Purple="0.99034146729" Red="0.00477468178925" Yellow="1.29808715183e-23"/>
         <hsvValue H="125.3952" S="174.5256" V="97.3608"/>
         <rgbValue B="98.0888" G="33.3416" R="44.3208"/>
      </colour>
   </object>
   <object id="10">
      <position global="right center" x="452" y="198"/>
      <shape BestResponse="F">
         <distribution F="0.800368501899" I="1.0956315376e-94" L="1.29100188348e-13" N="3.86466996646e-14" P="0.188380071766" T="0.00611942863678" U="0.00198235244686" V="1.58686332991e-13" W="9.35018149605e-08" X="0.00314931066034" Y="2.41088040093e-07" Z="1.04346089094e-13"/>
         <orientation value="15.0455291221"/>
         <skewness horizontal="symmetric" vertical="symmetric"/>
         <nbEdges value="10"/>
      </shape>
      <colour BestResponse="Blue">
         <distribution Blue="0.564874754446" Brown="8.76260546407e-11" Gray="0.383994947807" Green="1.19142084775e-06" Orange="3.88490730789e-08" Pink="0.0381005671317" Purple="0.0128252973069" Red="0.000203202950398" Yellow="3.15600555693e-13"/>
         <hsvValue H="103.275912409" S="95.5459854015" V="104.725060827"/>
         <rgbValue B="106.170316302" G="88.5562043796" R="66.1746958637"/>
      </colour>
   </object>
   <object id="11">
      <position global="center center" x="197" y="178"/>
      <shape BestResponse="U">
         <distribution F="6.22826571637e-07" I="0.0" L="6.17736269791e-10" N="8.39880313713e-87" P="0.0" T="7.32382443075e-41" U="0.836536319572" V="2.44038883064e-05" W="0.0" X="0.0" Y="0.162940823347" Z="0.000497829747948"/>
         <orientation value="13.1085135119"/>
         <skewness horizontal="left-skewed" vertical="symmetric"/>
         <nbEdges value="8"/>
      </shape>
      <colour BestResponse="Yellow">
         <distribution Blue="1.80504571245e-46" Brown="0.0188702523669" Gray="0.000143582872867" Green="0.000132143505258" Orange="0.0801097191459" Pink="0.00113256655418" Purple="1.07402193068e-36" Red="7.28303989692e-05" Yellow="0.899538905156"/>
         <hsvValue H="27.9150702427" S="152.600893997" V="142.279693487"/>
         <rgbValue B="59.1985951469" G="135.019157088" R="140.627713921"/>
      </colour>
   </object>
</timestamp>
