<timestamp time="447224.669604">
   <boundingBox height="467" width="620" x="77" y="23"/>
   <occluded>
      <object id="1"/>
   </occluded>
   <object id="0">
      <position global="center top" x="272" y="115"/>
      <shape BestResponse="L">
         <distribution F="5.80798389912e-16" I="0.000305365172552" L="0.999694634827" N="1.55685111515e-15" P="0.0" T="0.0" U="0.0" V="1.45199597478e-16" W="7.26365761345e-16" X="0.0" Y="4.11218666136e-16" Z="0.0"/>
         <orientation value="-12.3896744688"/>
         <skewness horizontal="right-skewed" vertical="bottom-skewed"/>
         <nbEdges value="6"/>
      </shape>
      <colour BestResponse="Orange">
         <distribution Blue="2.97483294642e-65" Brown="0.0110113228131" Gray="9.01104298618e-09" Green="6.98072271066e-18" Orange="0.712516373288" Pink="0.000753947138327" Purple="1.6716156271e-50" Red="0.00499709041625" Yellow="0.270721257333"/>
         <hsvValue H="17.3224852071" S="244.313609467" V="174.149408284"/>
         <rgbValue B="9.53624260355" G="103.255177515" R="172.540680473"/>
      </colour>
   </object>
   <object id="1">
      <position global="left bottom" x="70" y="388"/>
      <shape BestResponse="W">
         <distribution F="6.20735892313e-29" I="0.0" L="6.60770441006e-29" N="0.399907155825" P="2.48294356925e-28" T="0.0" U="0.0" V="0.0" W="0.600092844174" X="0.0" Y="8.14874379766e-13" Z="6.99120063958e-21"/>
         <orientation value="18.8936755998"/>
         <skewness horizontal="symmetric" vertical="symmetric"/>
         <nbEdges value="8"/>
      </shape>
      <colour BestResponse="Purple">
         <distribution Blue="2.51858058763e-13" Brown="4.93926995396e-17" Gray="0.00839609608156" Green="1.8311974213e-13" Orange="2.32006149573e-10" Pink="0.0321260541364" Purple="0.95742210553" Red="0.00205574401919" Yellow="7.27063752484e-19"/>
         <hsvValue H="135.305749597" S="127.249328318" V="61.7614185922"/>
         <rgbValue B="61.8344975819" G="33.306824288" R="47.6270822139"/>
      </colour>
   </object>
   <object id="2">
      <position global="right top" x="424" y="84"/>
      <shape BestResponse="T">
         <distribution F="0.000460435259208" I="0.0" L="5.35224057215e-29" N="1.73412594538e-29" P="0.0" T="0.97302858264" U="0.0" V="0.0265109821012" W="2.60118891806e-29" X="1.44543705426e-34" Y="3.94795645399e-22" Z="2.34107002626e-29"/>
         <orientation value="14.1916737478"/>
         <skewness horizontal="left-skewed" vertical="bottom-skewed"/>
         <nbEdges value="8"/>
      </shape>
      <colour BestResponse="Green">
         <distribution Blue="3.76079307276e-13" Brown="0.000552220097236" Gray="0.00196434917058" Green="0.993301524685" Orange="0.000354442482793" Pink="0.000107431294101" Purple="4.77687531444e-26" Red="1.76279591764e-06" Yellow="0.00371826947434"/>
         <hsvValue H="52.0345501956" S="143.748370274" V="117.024119948"/>
         <rgbValue B="51.8663624511" G="116.819426336" R="69.3539765319"/>
      </colour>
   </object>
   <object id="3">
      <position global="center center" x="255" y="172"/>
      <shape BestResponse="F">
         <distribution F="0.809955832442" I="0.0" L="4.27639478368e-28" N="3.13163795528e-09" P="5.56199425139e-10" T="1.3934544677e-09" U="0.19004415573" V="5.86050844639e-09" W="0.0" X="3.26910923211e-10" Y="5.17000504309e-10" Z="4.16595366287e-11"/>
         <orientation value="25.9593900837"/>
         <skewness horizontal="left-skewed" vertical="symmetric"/>
         <nbEdges value="10"/>
      </shape>
      <colour BestResponse="Gray">
         <distribution Blue="4.95972414539e-12" Brown="8.68952835732e-06" Gray="0.533766868006" Green="0.44363378717" Orange="0.000291386531402" Pink="0.0218946760216" Purple="7.39717115985e-13" Red="0.000171000479669" Yellow="0.000233592257109"/>
         <hsvValue H="51.9574759945" S="57.3936899863" V="101.808641975"/>
         <rgbValue B="78.6364883402" G="101.430727023" R="85.3065843621"/>
      </colour>
   </object>
   <object id="4">
      <position global="center top" x="286" y="143"/>
      <shape BestResponse="P">
         <distribution F="2.44088338323e-10" I="0.0" L="0.0" N="0.0" P="0.999999999755" T="2.28204896849e-14" U="0.0" V="0.0" W="7.68364643963e-13" X="7.25706979124e-21" Y="1.96567910689e-19" Z="2.38559874473e-13"/>
         <orientation value="15.2980565626"/>
         <skewness horizontal="right-skewed" vertical="symmetric"/>
         <nbEdges value="6"/>
      </shape>
      <colour BestResponse="Pink">
         <distribution Blue="3.29231797538e-36" Brown="0.0536829529157" Gray="0.000662226506049" Green="1.96048148833e-23" Orange="0.0828588555781" Pink="0.472237030863" Purple="4.25778259983e-20" Red="0.390543282103" Yellow="1.56520339183e-05"/>
         <hsvValue H="17.1388508892" S="108.74623803" V="153.799589603"/>
         <rgbValue B="88.3235294118" G="91.8891928865" R="152.923392613"/>
      </colour>
   </object>
   <object id="5">
      <position global="center center" x="236" y="231"/>
      <shape BestResponse="Y">
         <distribution F="6.11415624769e-22" I="0.0" L="0.0451457110552" N="0.0725966556151" P="0.0" T="2.35412034712e-07" U="4.19460642369e-09" V="2.150610923e-11" W="0.062392249888" X="0.0" Y="0.819102096149" Z="0.000763047664273"/>
         <orientation value="-7.99600688499"/>
         <skewness horizontal="right-skewed" vertical="top-skewed"/>
         <nbEdges value="6"/>
      </shape>
      <colour BestResponse="Brown">
         <distribution Blue="3.20531555255e-37" Brown="0.876973983781" Gray="2.79695998586e-08" Green="1.36407093997e-18" Orange="0.0968867712623" Pink="0.000379165723821" Purple="4.82029680318e-35" Red="0.0257384571603" Yellow="2.1594103381e-05"/>
         <hsvValue H="16.1886904762" S="226.910119048" V="98.1369047619"/>
         <rgbValue B="12.1023809524" G="58.7857142857" R="96.8077380952"/>
      </colour>
   </object>
   <object id="6">
      <position global="left top" x="200" y="68"/>
      <shape BestResponse="X">
         <distribution F="0.158649203547" I="0.0" L="0.0" N="0.0" P="0.0" T="0.0" U="0.0" V="0.0" W="0.0" X="0.841350796453" Y="0.0" Z="0.0"/>
         <orientation value="6.54495392864"/>
         <skewness horizontal="symmetric" vertical="symmetric"/>
         <nbEdges value="12"/>
      </shape>
      <colour BestResponse="Orange">
         <distribution Blue="1.40479711637e-58" Brown="0.127534106856" Gray="5.58568193514e-08" Green="1.27157299293e-27" Orange="0.551171204063" Pink="0.0137742078512" Purple="1.18734835243e-38" Red="0.307343095443" Yellow="0.000177329930294"/>
         <hsvValue H="9.62610619469" S="200.009587021" V="167.436578171"/>
         <rgbValue B="37.6305309735" G="78.8200589971" R="165.459439528"/>
      </colour>
   </object>
   <object id="7">
      <position global="left top" x="46" y="146"/>
      <shape BestResponse="I">
         <distribution F="0.0" I="1.0" L="0.0" N="0.0" P="0.0" T="0.0" U="0.0" V="0.0" W="3.84099901569e-17" X="0.0" Y="0.0" Z="0.0"/>
         <orientation value="-4.54296446533"/>
         <skewness horizontal="symmetric" vertical="symmetric"/>
         <nbEdges value="6"/>
      </shape>
      <colour BestResponse="Blue">
         <distribution Blue="0.999977119029" Brown="8.86099815801e-06" Gray="1.87149505419e-06" Green="4.71547777469e-12" Orange="9.62692754412e-10" Pink="1.00753591992e-05" Purple="1.53742105485e-10" Red="2.07199748074e-06" Yellow="7.75585220871e-19"/>
         <hsvValue H="98.0072463768" S="212.394323671" V="113.365338164"/>
         <rgbValue B="111.717995169" G="88.4438405797" R="21.3049516908"/>
      </colour>
   </object>
   <object id="8">
      <position global="right bottom" x="476" y="367"/>
      <shape BestResponse="V">
         <distribution F="0.103641315799" I="7.87620867764e-20" L="1.44308182928e-18" N="0.0" P="0.0" T="0.0" U="0.0450559935544" V="0.843162669538" W="0.000233045840335" X="0.0" Y="0.00790668464807" Z="2.90619777533e-07"/>
         <orientation value="29.5572835426"/>
         <skewness horizontal="left-skewed" vertical="top-skewed"/>
         <nbEdges value="6"/>
      </shape>
      <colour BestResponse="Blue">
         <distribution Blue="0.999765764057" Brown="0.000231896307524" Gray="9.94164965185e-08" Green="6.21894671474e-11" Orange="1.38127135273e-09" Pink="1.2689771235e-06" Purple="3.16657955162e-14" Red="9.69798490137e-07" Yellow="7.20591968505e-19"/>
         <hsvValue H="94.1918172157" S="249.635494155" V="95.3836344315"/>
         <rgbValue B="95.3044633369" G="82.821466525" R="4.16312433581"/>
      </colour>
   </object>
   <object id="9">
      <position global="left center" x="202" y="219"/>
      <shape BestResponse="U">
         <distribution F="0.0258239136043" I="0.0" L="0.000391686915756" N="0.0" P="0.0" T="0.0" U="0.869654214318" V="0.00335780124572" W="0.0" X="0.0" Y="0.000931115387456" Z="0.0998412685286"/>
         <orientation value="0.592229879274"/>
         <skewness horizontal="left-skewed" vertical="symmetric"/>
         <nbEdges value="9"/>
      </shape>
      <colour BestResponse="Yellow">
         <distribution Blue="2.66468873147e-51" Brown="0.00874846263388" Gray="4.38464198864e-08" Green="0.298313952474" Orange="0.144018004975" Pink="8.5006216294e-06" Purple="8.61875293016e-51" Red="2.57709369944e-06" Yellow="0.548908458356"/>
         <hsvValue H="28.8396718867" S="253.484712901" V="141.781506339"/>
         <rgbValue B="3.01118568233" G="135.83743475" R="140.902311708"/>
      </colour>
   </object>
   <object id="10">
      <position global="center center" x="272" y="214"/>
      <shape BestResponse="Z">
         <distribution F="0.0" I="0.0" L="1.61666098939e-09" N="5.06945844775e-06" P="0.0" T="0.0" U="0.0" V="5.67935138251e-32" W="0.387122404973" X="0.0" Y="0.0479738361933" Z="0.564898687758"/>
         <orientation value="29.2819276254"/>
         <skewness horizontal="symmetric" vertical="symmetric"/>
         <nbEdges value="8"/>
      </shape>
      <colour BestResponse="Blue">
         <distribution Blue="0.99645768469" Brown="0.00350263697351" Gray="2.29532429873e-07" Green="3.89298245323e-05" Orange="4.86927102628e-09" Pink="4.2004470637e-07" Purple="7.31337463412e-18" Red="9.40652490303e-08" Yellow="2.37662721914e-16"/>
         <hsvValue H="88.6995738636" S="248.006392045" V="103.6015625"/>
         <rgbValue B="97.3636363636" G="102.308238636" R="5.20880681818"/>
      </colour>
   </object>
   <object id="11">
      <position global="left center" x="121" y="174"/>
      <shape BestResponse="W">
         <distribution F="0.0" I="0.0" L="0.135364642677" N="0.0579240139327" P="1.63471321906e-22" T="0.0" U="0.0" V="0.0" W="0.795152978601" X="0.0" Y="0.0115583647885" Z="1.87771251352e-13"/>
         <orientation value="-20.7020359121"/>
         <skewness horizontal="right-skewed" vertical="bottom-skewed"/>
         <nbEdges value="10"/>
      </shape>
      <colour BestResponse="Green">
         <distribution Blue="1.08391517647e-26" Brown="0.00651499662062" Gray="1.7774573175e-05" Green="0.650357701722" Orange="0.00323712585742" Pink="9.50987443635e-06" Purple="7.2470392656e-39" Red="3.11012214577e-07" Yellow="0.33986258034"/>
         <hsvValue H="42.4919860627" S="197.156097561" V="132.648083624"/>
         <rgbValue B="32.0334494774" G="132.109407666" R="90.0933797909"/>
      </colour>
   </object>
</timestamp>
